gptchain/__init__.py
gptchain-1.0.0.dist-info/METADATA
gptchain-1.0.0.dist-info/WHEEL
gptchain-1.0.0.dist-info/entry_points.txt
gptchain-1.0.0.dist-info/top_level.txt
gptchain-1.0.0.dist-info/RECORD
