Metadata-Version: 2.1
Name: gptchain
Version: 1.0.0
Summary: Link multiple GPT prompts into a chain of responses.
Home-page: https://github.com/markshust/gptchain
Author: Mark Shust
Author-email: mark@shust.com
Requires-Dist: openai >=1.2.3
